README.md
setup.py
example/__init__.py
example/consumer.py
example/producer.py
jasyncq/__init__.py
jasyncq/util.py
jasyncq.egg-info/PKG-INFO
jasyncq.egg-info/SOURCES.txt
jasyncq.egg-info/dependency_links.txt
jasyncq.egg-info/not-zip-safe
jasyncq.egg-info/requires.txt
jasyncq.egg-info/top_level.txt
jasyncq/dispatcher/__init__.py
jasyncq/dispatcher/tasks.py
jasyncq/dispatcher/model/__init__.py
jasyncq/dispatcher/model/task.py
jasyncq/repository/__init__.py
jasyncq/repository/abstract.py
jasyncq/repository/tasks.py
jasyncq/repository/model/__init__.py
jasyncq/repository/model/task.py
tests/__init__.py
tests/test_let_if.py
tests/test_repository.py
tests/util.py