Metadata-Version: 2.1
Name: jasyncq
Version: 1.1.2
Summary: High reliability asynchronous queue using mysql(lock)
Home-page: https://github.com/pjongy/jasyncq
Author: pjongy
Author-email: hi.pjongy@gmail.com
License: UNKNOWN
Keywords: message queue,queue,distributed,microservice
Platform: UNKNOWN
Classifier: Programming Language :: Python :: 3.7
Classifier: Programming Language :: Python :: 3.8
Requires-Python: >=3.7
